processamento_imagens/__init__.py
processamento_imagens/filtros.py
processamento_imagens/transformacoes.py
processamento_imagens_ahaerdy-0.0.1.dist-info/licenses/LICENSE
processamento_imagens_ahaerdy-0.0.1.dist-info/METADATA
processamento_imagens_ahaerdy-0.0.1.dist-info/WHEEL
processamento_imagens_ahaerdy-0.0.1.dist-info/top_level.txt
processamento_imagens_ahaerdy-0.0.1.dist-info/RECORD
