Metadata-Version: 2.4
Name: processamento-imagens-ahaerdy
Version: 0.0.1
Summary: Pacote simples para aplicar transformações e filtros em imagens usando Python e Pillow.
Home-page: https://github.com/ahaerdy/processamento-imagens-ahaerdy
Author: Arthur Haerdy
Author-email: arthur.haerdy@gmail.com
Requires-Python: >=3.8
License-File: LICENSE
Requires-Dist: Pillow>=10.0.0
Dynamic: author
Dynamic: author-email
Dynamic: description
Dynamic: description-content-type
Dynamic: home-page
Dynamic: license-file
Dynamic: requires-dist
Dynamic: requires-python
Dynamic: summary
